[
  {
    "anonymous": false,
    "inputs": [
      {
        "indexed": true,
        "internalType": "address",
        "name": "adminAddress",
        "type": "address"
      }
    ],
    "name": "AdminAddressSet",
    "type": "event"
  },
  {
    "anonymous": false,
    "inputs": [
      {
        "indexed": true,
        "internalType": "address",
        "name": "asset",
        "type": "address"
      },
      {
        "indexed": false,
        "internalType": "uint16",
        "name": "tokenType",
        "type": "uint16"
      },
      {
        "indexed": false,
        "internalType": "bool",
        "name": "allowed",
        "type": "bool"
      }
    ],
    "name": "AssetWhitelisted",
    "type": "event"
  },
  {
    "anonymous": false,
    "inputs": [
      {
        "indexed": true,
        "internalType": "address",
        "name": "asset",
        "type": "address"
      }
    ],
    "name": "AssetWhitelistedRemoved",
    "type": "event"
  },
  {
    "anonymous": false,
    "inputs": [
      {
        "indexed": true,
        "internalType": "bytes32",
        "name": "name",
        "type": "bytes32"
      },
      {
        "indexed": true,
        "internalType": "address",
        "name": "addr",
        "type": "address"
      }
    ],
    "name": "GovernanceAddressMapped",
    "type": "event"
  },
  {
    "anonymous": false,
    "inputs": [
      {
        "indexed": true,
        "internalType": "address",
        "name": "governanceAddress",
        "type": "address"
      }
    ],
    "name": "GovernanceAddressSet",
    "type": "event"
  },
  {
    "anonymous": false,
    "inputs": [
      {
        "indexed": true,
        "internalType": "address",
        "name": "assetHandler",
        "type": "address"
      }
    ],
    "name": "SetAssetHandler",
    "type": "event"
  },
  {
    "anonymous": false,
    "inputs": [
      {
        "indexed": false,
        "internalType": "uint256",
        "name": "version",
        "type": "uint256"
      }
    ],
    "name": "SetVaultStorageVersion",
    "type": "event"
  },
  {
    "anonymous": false,
    "inputs": [
      {
        "indexed": true,
        "internalType": "address",
        "name": "treasuryAddress",
        "type": "address"
      }
    ],
    "name": "TreasuryAddressSet",
    "type": "event"
  },
  {
    "anonymous": false,
    "inputs": [
      {
        "indexed": true,
        "internalType": "address",
        "name": "asset",
        "type": "address"
      },
      {
        "indexed": false,
        "internalType": "uint16",
        "name": "tokenType",
        "type": "uint16"
      }
    ],
    "name": "UnderlyingAssetAdded",
    "type": "event"
  },
  {
    "anonymous": false,
    "inputs": [
      {
        "indexed": true,
        "internalType": "address",
        "name": "asset",
        "type": "address"
      }
    ],
    "name": "UnderlyingAssetRemoved",
    "type": "event"
  },
  {
    "anonymous": false,
    "inputs": [
      {
        "indexed": true,
        "internalType": "address",
        "name": "vault",
        "type": "address"
      },
      {
        "indexed": true,
        "internalType": "address",
        "name": "manager",
        "type": "address"
      },
      {
        "indexed": true,
        "internalType": "address",
        "name": "underlyingAsset",
        "type": "address"
      },
      {
        "indexed": false,
        "internalType": "string",
        "name": "name",
        "type": "string"
      },
      {
        "indexed": false,
        "internalType": "string",
        "name": "symbol",
        "type": "string"
      },
      {
        "indexed": false,
        "internalType": "uint256",
        "name": "maxCapacity",
        "type": "uint256"
      }
    ],
    "name": "VaultCreated",
    "type": "event"
  },
  {
    "anonymous": false,
    "inputs": [
      {
        "indexed": true,
        "internalType": "address",
        "name": "oldImplementation",
        "type": "address"
      },
      {
        "indexed": true,
        "internalType": "address",
        "name": "newImplementation",
        "type": "address"
      }
    ],
    "name": "VaultImplementationUpdated",
    "type": "event"
  },
  {
    "anonymous": false,
    "inputs": [
      {
        "indexed": true,
        "internalType": "address",
        "name": "vault",
        "type": "address"
      },
      {
        "indexed": true,
        "internalType": "address",
        "name": "newImplementation",
        "type": "address"
      }
    ],
    "name": "VaultUpgraded",
    "type": "event"
  },
  {
    "inputs": [],
    "name": "admin",
    "outputs": [
      {
        "internalType": "address",
        "name": "",
        "type": "address"
      }
    ],
    "stateMutability": "view",
    "type": "function"
  },
  {
    "inputs": [
      {
        "internalType": "address",
        "name": "asset",
        "type": "address"
      }
    ],
    "name": "assetIndex",
    "outputs": [
      {
        "internalType": "uint256",
        "name": "",
        "type": "uint256"
      }
    ],
    "stateMutability": "view",
    "type": "function"
  },
  {
    "inputs": [],
    "name": "creationFee",
    "outputs": [
      {
        "internalType": "uint256",
        "name": "",
        "type": "uint256"
      }
    ],
    "stateMutability": "view",
    "type": "function"
  },
  {
    "inputs": [
      {
        "internalType": "uint256",
        "name": "index",
        "type": "uint256"
      }
    ],
    "name": "deployedVaults",
    "outputs": [
      {
        "internalType": "address",
        "name": "",
        "type": "address"
      }
    ],
    "stateMutability": "view",
    "type": "function"
  },
  {
    "inputs": [
      {
        "internalType": "address",
        "name": "_asset",
        "type": "address"
      },
      {
        "internalType": "uint256",
        "name": "_amount",
        "type": "uint256"
      }
    ],
    "name": "emergencyRecoverAsset",
    "outputs": [],
    "stateMutability": "nonpayable",
    "type": "function"
  },
  {
    "inputs": [],
    "name": "getAssetHandler",
    "outputs": [
      {
        "internalType": "address",
        "name": "",
        "type": "address"
      }
    ],
    "stateMutability": "view",
    "type": "function"
  },
  {
    "inputs": [
      {
        "internalType": "address",
        "name": "_asset",
        "type": "address"
      }
    ],
    "name": "getAssetType",
    "outputs": [
      {
        "internalType": "uint16",
        "name": "",
        "type": "uint16"
      }
    ],
    "stateMutability": "view",
    "type": "function"
  },
  {
    "inputs": [],
    "name": "getDeployedVaults",
    "outputs": [
      {
        "internalType": "address[]",
        "name": "",
        "type": "address[]"
      }
    ],
    "stateMutability": "view",
    "type": "function"
  },
  {
    "inputs": [
      {
        "internalType": "address",
        "name": "_vault",
        "type": "address"
      }
    ],
    "name": "getDetailedVaultInfo",
    "outputs": [
      {
        "internalType": "address",
        "name": "underlyingAsset",
        "type": "address"
      },
      {
        "internalType": "uint256",
        "name": "totalShares",
        "type": "uint256"
      },
      {
        "internalType": "uint256",
        "name": "totalAssetsAmount",
        "type": "uint256"
      },
      {
        "internalType": "uint256",
        "name": "sharePrice",
        "type": "uint256"
      },
      {
        "internalType": "uint256",
        "name": "maxCap",
        "type": "uint256"
      },
      {
        "internalType": "uint256",
        "name": "minDeposit",
        "type": "uint256"
      }
    ],
    "stateMutability": "view",
    "type": "function"
  },
  {
    "inputs": [],
    "name": "getFactoryStats",
    "outputs": [
      {
        "internalType": "uint256",
        "name": "totalVaults",
        "type": "uint256"
      },
      {
        "internalType": "uint256",
        "name": "totalValueLocked",
        "type": "uint256"
      },
      {
        "internalType": "uint256",
        "name": "whitelistedAssetsCount",
        "type": "uint256"
      },
      {
        "internalType": "address[]",
        "name": "topVaultsByTVL",
        "type": "address[]"
      }
    ],
    "stateMutability": "view",
    "type": "function"
  },
  {
    "inputs": [
      {
        "internalType": "address",
        "name": "_asset",
        "type": "address"
      }
    ],
    "name": "getTokenType",
    "outputs": [
      {
        "internalType": "uint16",
        "name": "",
        "type": "uint16"
      }
    ],
    "stateMutability": "view",
    "type": "function"
  },
  {
    "inputs": [],
    "name": "getVaultCount",
    "outputs": [
      {
        "internalType": "uint256",
        "name": "",
        "type": "uint256"
      }
    ],
    "stateMutability": "view",
    "type": "function"
  },
  {
    "inputs": [
      {
        "internalType": "address",
        "name": "_vault",
        "type": "address"
      }
    ],
    "name": "getVaultInfo",
    "outputs": [
      {
        "internalType": "address",
        "name": "manager",
        "type": "address"
      },
      {
        "internalType": "address",
        "name": "underlyingAsset",
        "type": "address"
      },
      {
        "internalType": "uint256",
        "name": "totalAssets",
        "type": "uint256"
      },
      {
        "internalType": "uint256",
        "name": "totalSupply",
        "type": "uint256"
      },
      {
        "internalType": "uint256",
        "name": "maxCapacity",
        "type": "uint256"
      },
      {
        "internalType": "bool",
        "name": "isPaused",
        "type": "bool"
      },
      {
        "internalType": "uint256",
        "name": "sharePrice",
        "type": "uint256"
      }
    ],
    "stateMutability": "view",
    "type": "function"
  },
  {
    "inputs": [
      {
        "internalType": "address",
        "name": "_vault",
        "type": "address"
      }
    ],
    "name": "getVaultManager",
    "outputs": [
      {
        "internalType": "address",
        "name": "",
        "type": "address"
      }
    ],
    "stateMutability": "view",
    "type": "function"
  },
  {
    "inputs": [
      {
        "internalType": "address",
        "name": "_manager",
        "type": "address"
      }
    ],
    "name": "getVaultsByManager",
    "outputs": [
      {
        "internalType": "address[]",
        "name": "",
        "type": "address[]"
      }
    ],
    "stateMutability": "view",
    "type": "function"
  },
  {
    "inputs": [],
    "name": "governance",
    "outputs": [
      {
        "internalType": "address",
        "name": "",
        "type": "address"
      }
    ],
    "stateMutability": "view",
    "type": "function"
  },
  {
    "inputs": [],
    "name": "implementationVersion",
    "outputs": [
      {
        "internalType": "uint32",
        "name": "",
        "type": "uint32"
      }
    ],
    "stateMutability": "view",
    "type": "function"
  },
  {
    "inputs": [
      {
        "internalType": "address",
        "name": "_asset",
        "type": "address"
      }
    ],
    "name": "isAssetWhitelisted",
    "outputs": [
      {
        "internalType": "bool",
        "name": "",
        "type": "bool"
      }
    ],
    "stateMutability": "view",
    "type": "function"
  },
  {
    "inputs": [
      {
        "internalType": "address",
        "name": "_vault",
        "type": "address"
      }
    ],
    "name": "isValidVault",
    "outputs": [
      {
        "internalType": "bool",
        "name": "",
        "type": "bool"
      }
    ],
    "stateMutability": "view",
    "type": "function"
  },
  {
    "inputs": [
      {
        "internalType": "address",
        "name": "vault",
        "type": "address"
      }
    ],
    "name": "isVault",
    "outputs": [
      {
        "internalType": "bool",
        "name": "",
        "type": "bool"
      }
    ],
    "stateMutability": "view",
    "type": "function"
  },
  {
    "inputs": [],
    "name": "maxCapacityLimit",
    "outputs": [
      {
        "internalType": "uint256",
        "name": "",
        "type": "uint256"
      }
    ],
    "stateMutability": "view",
    "type": "function"
  },
  {
    "inputs": [],
    "name": "minCapacityLimit",
    "outputs": [
      {
        "internalType": "uint256",
        "name": "",
        "type": "uint256"
      }
    ],
    "stateMutability": "view",
    "type": "function"
  },
  {
    "inputs": [],
    "name": "owner",
    "outputs": [
      {
        "internalType": "address",
        "name": "",
        "type": "address"
      }
    ],
    "stateMutability": "view",
    "type": "function"
  },
  {
    "inputs": [],
    "name": "paused",
    "outputs": [
      {
        "internalType": "bool",
        "name": "",
        "type": "bool"
      }
    ],
    "stateMutability": "view",
    "type": "function"
  },
  {
    "inputs": [],
    "name": "proxyAdmin",
    "outputs": [
      {
        "internalType": "address",
        "name": "",
        "type": "address"
      }
    ],
    "stateMutability": "view",
    "type": "function"
  },
  {
    "inputs": [
      {
        "internalType": "address",
        "name": "_adminAddress",
        "type": "address"
      }
    ],
    "name": "setAdminAddress",
    "outputs": [],
    "stateMutability": "nonpayable",
    "type": "function"
  },
  {
    "inputs": [
      {
        "internalType": "address",
        "name": "_treasuryAddress",
        "type": "address"
      }
    ],
    "name": "setTreasuryAddress",
    "outputs": [],
    "stateMutability": "nonpayable",
    "type": "function"
  },
  {
    "inputs": [
      {
        "internalType": "address",
        "name": "asset",
        "type": "address"
      }
    ],
    "name": "tokenType",
    "outputs": [
      {
        "internalType": "uint16",
        "name": "",
        "type": "uint16"
      }
    ],
    "stateMutability": "view",
    "type": "function"
  },
  {
    "inputs": [],
    "name": "treasury",
    "outputs": [
      {
        "internalType": "address",
        "name": "",
        "type": "address"
      }
    ],
    "stateMutability": "view",
    "type": "function"
  },
  {
    "inputs": [
      {
        "internalType": "address",
        "name": "asset",
        "type": "address"
      }
    ],
    "name": "underlyingAssetAllowed",
    "outputs": [
      {
        "internalType": "bool",
        "name": "",
        "type": "bool"
      }
    ],
    "stateMutability": "view",
    "type": "function"
  },
  {
    "inputs": [],
    "name": "vaultImplementation",
    "outputs": [
      {
        "internalType": "address",
        "name": "",
        "type": "address"
      }
    ],
    "stateMutability": "view",
    "type": "function"
  },
  {
    "inputs": [
      {
        "internalType": "address",
        "name": "vault",
        "type": "address"
      }
    ],
    "name": "vaultIndex",
    "outputs": [
      {
        "internalType": "uint256",
        "name": "",
        "type": "uint256"
      }
    ],
    "stateMutability": "view",
    "type": "function"
  },
  {
    "inputs": [
      {
        "internalType": "address",
        "name": "vault",
        "type": "address"
      }
    ],
    "name": "vaultManager",
    "outputs": [
      {
        "internalType": "address",
        "name": "",
        "type": "address"
      }
    ],
    "stateMutability": "view",
    "type": "function"
  },
  {
    "inputs": [],
    "name": "vaultStorageVersion",
    "outputs": [
      {
        "internalType": "uint256",
        "name": "",
        "type": "uint256"
      }
    ],
    "stateMutability": "view",
    "type": "function"
  },
  {
    "inputs": [],
    "name": "version",
    "outputs": [
      {
        "internalType": "string",
        "name": "",
        "type": "string"
      }
    ],
    "stateMutability": "pure",
    "type": "function"
  },
  {
    "inputs": [
      {
        "internalType": "uint256",
        "name": "index",
        "type": "uint256"
      }
    ],
    "name": "whitelistedAssets",
    "outputs": [
      {
        "internalType": "address",
        "name": "",
        "type": "address"
      }
    ],
    "stateMutability": "view",
    "type": "function"
  }
]
